{
  "schemaVersion": 1,
  "branch": "main",
  "baseRef": "origin/main",
  "sourceCommit": "802300e",
  "committedAt": "2026-04-29T22:52:31+08:00",
  "versionType": "patch",
  "title": "优化管理员配置中心参数覆盖",
  "changes": [
    "配置中心补齐实例隔离、模型、方案页预热、视觉和前端限制配置项。",
    "优化多 env 写入目标与进程环境变量覆盖提示。",
    "更新配置中心页面、默认前端配置和配置文档说明。",
    "补充配置中心回归并修正报告 V3 发布保守档测试隔离。"
  ],
  "changedFiles": [
    "docs/agent/admin-ops.md",
    "tests/test_api_comprehensive.py",
    "tests/test_security_regression.py",
    "web/CONFIG.md",
    "web/index.html",
    "web/server.py",
    "web/server_modules/admin_config_center.py",
    "web/site-config.js"
  ]
}
